cssmediaquery/__init__.py
cssmediaquery/__version__.py
cssmediaquery-0.0.1.dist-info/DESCRIPTION.rst
cssmediaquery-0.0.1.dist-info/METADATA
cssmediaquery-0.0.1.dist-info/RECORD
cssmediaquery-0.0.1.dist-info/WHEEL
cssmediaquery-0.0.1.dist-info/metadata.json
cssmediaquery-0.0.1.dist-info/top_level.txt
